{
    "version": "1.9",
    "name": "misp-custom-miner-pddk",
    "author": "pd-dk",
    "author_email": "pddk@onet.eu",
    "description": "Custom minemeld miner for extracting tagged attributes from MISP",
    "url": "https://github.com/pd-dk/misp-custom-miner",
    "entry_points": {
        "minemeld_nodes": {
            "mispcustomminer.MISPMiner": "mispcustomminer.node:MISPMiner"
        },
        "minemeld_prototypes": {
            "mispcustomminer.prototypes": "mispcustomminer:prototypes"
        }
    },
    "manifest_version": 0
}
